nanopie/__init__.py
nanopie/fields.py
nanopie/globals.py
nanopie/handler.py
nanopie/logger.py
nanopie/model.py
nanopie/proxy.py
nanopie/auth/__init__.py
nanopie/auth/base.py
nanopie/auth/http_api_key.py
nanopie/auth/http_basic.py
nanopie/auth/http_oauth2_bearer_jwt.py
nanopie/auth/creds/__init__.py
nanopie/auth/creds/jwt.py
nanopie/auth/creds/key.py
nanopie/auth/creds/user_credential.py
nanopie/logging/__init__.py
nanopie/logging/base.py
nanopie/logging/fluentd.py
nanopie/logging/formatter.py
nanopie/logging/logstash.py
nanopie/logging/stackdriver.py
nanopie/logging/handlers/__init__.py
nanopie/logging/handlers/logstash.py
nanopie/logging/handlers/stackdriver.py
nanopie/misc/__init__.py
nanopie/misc/errors/__init__.py
nanopie/misc/errors/base.py
nanopie/misc/errors/validation.py
nanopie/serialization/__init__.py
nanopie/serialization/base.py
nanopie/serialization/http.py
nanopie/serialization/helpers/__init__.py
nanopie/serialization/helpers/base.py
nanopie/serialization/helpers/json.py
nanopie/services/__init__.py
nanopie/services/base.py
nanopie/services/http/__init__.py
nanopie/services/http/base.py
nanopie/services/http/flask_svc.py
nanopie/services/http/foundation.py
nanopie/services/http/io.py
nanopie/services/http/methods.py
nanopie/tracing/__init__.py
nanopie/tracing/base.py
nanopie/tracing/http_w3c_trace_ctx.py
nanopie/tracing/jaeger.py
nanopie/tracing/zipkin.py
nanopie-0.1.0.dist-info/LICENSE
nanopie-0.1.0.dist-info/METADATA
nanopie-0.1.0.dist-info/WHEEL
nanopie-0.1.0.dist-info/top_level.txt
nanopie-0.1.0.dist-info/RECORD
