Metadata-Version: 2.1
Name: nanopie
Version: 0.1.0
Summary: A lightweight framework for building Python microservices and API services.
Home-page: https://github.com/michaelawyu/nanopie
Author: michaelawyu
Author-email: michael.a.w.yu@gmail.com
Maintainer: michaelawyu
Maintainer-email: michael.a.w.yu@gmail.com
License: Apache License 2.0
Project-URL: Source, https://github.com/michaelawyu/nanopie
Project-URL: Documentation, https://nanopie.readthedocs.io
Project-URL: Issue Tracker, https://github.com/michaelawyu/nanopie/issues
Platform: UNKNOWN
Classifier: Development Status :: 3 - Alpha
Classifier: Environment :: Web Environment
Classifier: License :: OSI Approved :: Apache Software License
Classifier: Operating System :: OS Independent
Classifier: Topic :: Internet
Classifier: Topic :: Software Development :: Libraries :: Application Frameworks
Classifier: Topic :: Software Development :: Libraries :: Python Modules
Classifier: Programming Language :: Python :: 3
Classifier: Programming Language :: Python :: 3.5
Classifier: Programming Language :: Python :: 3.6
Classifier: Programming Language :: Python :: 3.7
Classifier: Programming Language :: Python :: 3.8
Requires-Python: >3.4
Provides-Extra: dev
Requires-Dist: pylint ; extra == 'dev'
Requires-Dist: pytest ; extra == 'dev'
Requires-Dist: black ; extra == 'dev'
Requires-Dist: opentelemetry-api ; extra == 'dev'
Requires-Dist: opentelemetry-sdk ; extra == 'dev'
Requires-Dist: flask ; extra == 'dev'
Requires-Dist: pyjwt ; extra == 'dev'
Requires-Dist: cryptography ; extra == 'dev'
Requires-Dist: twine ; extra == 'dev'
Provides-Extra: docs
Requires-Dist: mkdocs ; extra == 'docs'
Requires-Dist: mkdocs-material ; extra == 'docs'
